{
  "db_name": "MySQL",
  "query": "select\n                id,\n                client_id,\n                purchase_order_id,\n                quotes_id,\n                contract_id,\n                tenant_id,\n                delivery_date,\n                timezone,\n                currency,\n                billing_info_id,\n                invoice_address_id\n            from tachyon_apps_delivery.delivery_slips where id = ?",
  "describe": {
    "columns": [
      {
        "ordinal": 0,
        "name": "id",
        "type_info": {
          "type": "VarString",
          "flags": "NOT_NULL | PRIMARY_KEY | UNIQUE_KEY | NO_DEFAULT_VALUE",
          "max_size": 116
        }
      },
      {
        "ordinal": 1,
        "name": "client_id",
        "type_info": {
          "type": "VarString",
          "flags": "NOT_NULL | NO_DEFAULT_VALUE",
          "max_size": 116
        }
      },
      {
        "ordinal": 2,
        "name": "purchase_order_id",
        "type_info": {
          "type": "VarString",
          "flags": "NOT_NULL | NO_DEFAULT_VALUE",
          "max_size": 116
        }
      },
      {
        "ordinal": 3,
        "name": "quotes_id",
        "type_info": {
          "type": "VarString",
          "flags": "",
          "max_size": 116
        }
      },
      {
        "ordinal": 4,
        "name": "contract_id",
        "type_info": {
          "type": "VarString",
          "flags": "NOT_NULL | NO_DEFAULT_VALUE",
          "max_size": 116
        }
      },
      {
        "ordinal": 5,
        "name": "tenant_id",
        "type_info": {
          "type": "VarString",
          "flags": "NOT_NULL | PRIMARY_KEY | NO_DEFAULT_VALUE",
          "max_size": 116
        }
      },
      {
        "ordinal": 6,
        "name": "delivery_date",
        "type_info": {
          "type": "Datetime",
          "flags": "NOT_NULL | BINARY | NO_DEFAULT_VALUE",
          "max_size": 19
        }
      },
      {
        "ordinal": 7,
        "name": "timezone",
        "type_info": {
          "type": "VarString",
          "flags": "NOT_NULL | NO_DEFAULT_VALUE",
          "max_size": 200
        }
      },
      {
        "ordinal": 8,
        "name": "currency",
        "type_info": {
          "type": "VarString",
          "flags": "NOT_NULL | NO_DEFAULT_VALUE",
          "max_size": 12
        }
      },
      {
        "ordinal": 9,
        "name": "billing_info_id",
        "type_info": {
          "type": "VarString",
          "flags": "NOT_NULL | NO_DEFAULT_VALUE",
          "max_size": 116
        }
      },
      {
        "ordinal": 10,
        "name": "invoice_address_id",
        "type_info": {
          "type": "VarString",
          "flags": "NOT_NULL | NO_DEFAULT_VALUE",
          "max_size": 116
        }
      }
    ],
    "parameters": {
      "Right": 1
    },
    "nullable": [
      false,
      false,
      false,
      true,
      false,
      false,
      false,
      false,
      false,
      false,
      false
    ]
  },
  "hash": "020f65ab22c003e9d9aa58ef5e6bbf32c45b9062ee8f9ce2e68b3af42621e5ed"
}
