{
  "db_name": "MySQL",
  "query": "\n            SELECT\n                id, tenant_id, product_id,\n                quantity_on_hand, quantity_reserved,\n                quantity_available, low_stock_threshold,\n                track_inventory as \"track_inventory: bool\",\n                created_at, updated_at\n            FROM tachyon_apps_order.product_stocks\n            WHERE tenant_id = ? AND product_id = ?\n            ",
  "describe": {
    "columns": [
      {
        "ordinal": 0,
        "name": "id",
        "type_info": {
          "type": "VarString",
          "flags": "NOT_NULL | PRIMARY_KEY | NO_DEFAULT_VALUE",
          "max_size": 136
        }
      },
      {
        "ordinal": 1,
        "name": "tenant_id",
        "type_info": {
          "type": "VarString",
          "flags": "NOT_NULL | MULTIPLE_KEY | NO_DEFAULT_VALUE",
          "max_size": 116
        }
      },
      {
        "ordinal": 2,
        "name": "product_id",
        "type_info": {
          "type": "VarString",
          "flags": "NOT_NULL | NO_DEFAULT_VALUE",
          "max_size": 136
        }
      },
      {
        "ordinal": 3,
        "name": "quantity_on_hand",
        "type_info": {
          "type": "Long",
          "flags": "NOT_NULL",
          "max_size": 11
        }
      },
      {
        "ordinal": 4,
        "name": "quantity_reserved",
        "type_info": {
          "type": "Long",
          "flags": "NOT_NULL",
          "max_size": 11
        }
      },
      {
        "ordinal": 5,
        "name": "quantity_available",
        "type_info": {
          "type": "Long",
          "flags": "NOT_NULL",
          "max_size": 11
        }
      },
      {
        "ordinal": 6,
        "name": "low_stock_threshold",
        "type_info": {
          "type": "Long",
          "flags": "NOT_NULL",
          "max_size": 11
        }
      },
      {
        "ordinal": 7,
        "name": "track_inventory: bool",
        "type_info": {
          "type": "Tiny",
          "flags": "NOT_NULL",
          "max_size": 1
        }
      },
      {
        "ordinal": 8,
        "name": "created_at",
        "type_info": {
          "type": "Timestamp",
          "flags": "NOT_NULL | BINARY | TIMESTAMP",
          "max_size": 19
        }
      },
      {
        "ordinal": 9,
        "name": "updated_at",
        "type_info": {
          "type": "Timestamp",
          "flags": "NOT_NULL | BINARY | TIMESTAMP | ON_UPDATE_NOW",
          "max_size": 19
        }
      }
    ],
    "parameters": {
      "Right": 2
    },
    "nullable": [
      false,
      false,
      false,
      false,
      false,
      false,
      false,
      false,
      false,
      false
    ]
  },
  "hash": "5ff7440fdc07ea62649f0003666133029f60690bbd3ce29e3873ea19e81ef571"
}
